{"cameraMode":{"drawMode":0,"name":"Shaded","section":"Shading Mode"},"sceneLighting":true,"audioPlay":false,"sceneViewState":{"m_AlwaysRefresh":false,"showFog":true,"showSkybox":true,"showFlares":true,"showImageEffects":true,"showParticleSystems":true,"showVisualEffectGraphs":true,"m_FxEnabled":true},"in2DMode":false,"pivot":{"x":28.788265228271486,"y":26.061981201171876,"z":-17.335281372070314},"rotation":{"x":0.07176641374826431,"y":0.37959274649620058,"z":0.029550373554229738,"w":-0.9218931794166565},"size":10.0,"orthographic":false}